sqlrecorder/__init__.py
sqlrecorder/main.py
sqlrecorder-1.0.dist-info/LICENSE.md
sqlrecorder-1.0.dist-info/METADATA
sqlrecorder-1.0.dist-info/WHEEL
sqlrecorder-1.0.dist-info/top_level.txt
sqlrecorder-1.0.dist-info/RECORD
