Metadata-Version: 2.1
Name: sqlrecorder
Version: 1.0
Summary: Python Wrapper for use in recording the success or failure of any functions to a SQL table, along with any respective arguments or keyword arguments
Home-page: https://github.com/pauldewilson/SQLRecorder
Author: Paul Wilson
Author-email: pauldewilson@gmail.com
License: UNKNOWN
Project-URL: Bug Tracker, https://github.com/pauldewilson/SQLRecorder/issues
Platform: UNKNOWN
Classifier: Programming Language :: Python :: 3
Classifier: License :: OSI Approved :: MIT License
Classifier: Operating System :: OS Independent
Requires-Python: >=3.6
License-File: LICENSE.md
